plotext_plus/__init__.py
plotext_plus/__main__.py
plotext_plus/_api.py
plotext_plus/_build.py
plotext_plus/_core.py
plotext_plus/_date.py
plotext_plus/_default.py
plotext_plus/_dict.py
plotext_plus/_doc.py
plotext_plus/_doc_utils.py
plotext_plus/_figure.py
plotext_plus/_global.py
plotext_plus/_matrix.py
plotext_plus/_monitor.py
plotext_plus/_output.py
plotext_plus/_shtab.py
plotext_plus/_themes.py
plotext_plus/_utility.py
plotext_plus/api.py
plotext_plus/charts.py
plotext_plus/core.py
plotext_plus/mcp_cli.py
plotext_plus/mcp_server.py
plotext_plus/plotext_cli.py
plotext_plus/plotting.py
plotext_plus/themes.py
plotext_plus/utilities.py
plotext_plus/utils.py
plotext_plus-1.0.10.dist-info/METADATA
plotext_plus-1.0.10.dist-info/WHEEL
plotext_plus-1.0.10.dist-info/entry_points.txt
plotext_plus-1.0.10.dist-info/licenses/LICENSE
plotext_plus-1.0.10.dist-info/RECORD
