Metadata-Version: 2.4
Name: plotext_plus
Version: 1.0.10
Summary: Modern terminal plotting library with enhanced visual features, themes, and AI integration
Project-URL: Homepage, https://github.com/ccmitchellusa/plotext_plus
Project-URL: Repository, https://github.com/ccmitchellusa/plotext_plus.git
Project-URL: Issues, https://github.com/ccmitchellusa/plotext_plus/issues
Project-URL: Documentation, https://github.com/ccmitchellusa/plotext_plus/tree/main/docs
Author-email: Chris Mitchell <chris@ccmitchellusa.com>
License-Expression: MIT
License-File: LICENSE
Keywords: ai,charts,cli,graphs,mcp,plotting,terminal,visualization
Classifier: Development Status :: 4 - Beta
Classifier: Intended Audience :: Developers
Classifier: Intended Audience :: Science/Research
Classifier: License :: OSI Approved :: MIT License
Classifier: Operating System :: OS Independent
Classifier: Programming Language :: Python :: 3
Classifier: Programming Language :: Python :: 3.11
Classifier: Programming Language :: Python :: 3.12
Classifier: Programming Language :: Python :: 3.13
Classifier: Topic :: Scientific/Engineering :: Visualization
Classifier: Topic :: Software Development :: Libraries :: Python Modules
Classifier: Topic :: Terminals
Requires-Python: >=3.11
Requires-Dist: chuk-mcp-server>=0.3.5
Requires-Dist: chuk-term>=0.1.0
Requires-Dist: shtab>=1.7.2
Provides-Extra: completion
Requires-Dist: shtab; extra == 'completion'
Provides-Extra: image
Requires-Dist: pillow>=8.4; extra == 'image'
Provides-Extra: mcp
Requires-Dist: chuk-mcp-server>=0.3.5; extra == 'mcp'
Provides-Extra: video
Requires-Dist: ffpyplayer>=4.3.5; extra == 'video'
Requires-Dist: opencv-python>=4.5.5; extra == 'video'
Requires-Dist: pafy>=0.5.5; extra == 'video'
Requires-Dist: pillow>=8.4; extra == 'video'
Requires-Dist: youtube-dl==2020.12.2; extra == 'video'
